MANIFEST.in
README.rst
requirements.txt
setup.py
pluggage.egg-info/PKG-INFO
pluggage.egg-info/SOURCES.txt
pluggage.egg-info/dependency_links.txt
pluggage.egg-info/entry_points.txt
pluggage.egg-info/top_level.txt
src/pluggage/__init__.py
src/pluggage/errors.py
src/pluggage/factory_plugin.py
src/pluggage/loaders.py
src/pluggage/plugins.py
src/pluggage/registry.py