Metadata-Version: 1.0
Name: pluggage
Version: 0.0.4
Summary: Plugin, dynamic loading and factory utility library 
Home-page: https://pluggage.readthedocs.org/en/latest/
Author: Dave Evans
Author-email: evansde77.github@gmail.com
License: UNKNOWN
Platform: UNKNOWN
